odoo/addons/account_invoice_mode_daily/README.rst
odoo/addons/account_invoice_mode_daily/__init__.py
odoo/addons/account_invoice_mode_daily/__manifest__.py
odoo/addons/account_invoice_mode_daily/data/ir_cron.xml
odoo/addons/account_invoice_mode_daily/data/queue_job_data.xml
odoo/addons/account_invoice_mode_daily/i18n/account_invoice_mode_daily.pot
odoo/addons/account_invoice_mode_daily/i18n/es.po
odoo/addons/account_invoice_mode_daily/i18n/it.po
odoo/addons/account_invoice_mode_daily/models/__init__.py
odoo/addons/account_invoice_mode_daily/models/res_company.py
odoo/addons/account_invoice_mode_daily/models/res_config_settings.py
odoo/addons/account_invoice_mode_daily/models/res_partner.py
odoo/addons/account_invoice_mode_daily/models/sale_order.py
odoo/addons/account_invoice_mode_daily/readme/CONTRIBUTORS.rst
odoo/addons/account_invoice_mode_daily/readme/DESCRIPTION.rst
odoo/addons/account_invoice_mode_daily/static/description/icon.png
odoo/addons/account_invoice_mode_daily/static/description/index.html
odoo/addons/account_invoice_mode_daily/tests/__init__.py
odoo/addons/account_invoice_mode_daily/tests/test_invoice_mode_daily.py
odoo/addons/account_invoice_mode_daily/views/res_config_settings_views.xml
odoo14_addon_account_invoice_mode_daily-14.0.1.0.1.dev5.dist-info/METADATA
odoo14_addon_account_invoice_mode_daily-14.0.1.0.1.dev5.dist-info/WHEEL
odoo14_addon_account_invoice_mode_daily-14.0.1.0.1.dev5.dist-info/top_level.txt
odoo14_addon_account_invoice_mode_daily-14.0.1.0.1.dev5.dist-info/RECORD
